Workbook

Sheet Introduction
A1: GoEasy Firm Introduction:
B3: GoEasy is a Canadian financial services company that focuses on helping people who may not qualify for traditional credit. Through its brands like easyfinancial, easyhome, and LendCare offers everything from personal loans to lease‑to‑own furniture, appliances, and point‑of‑sale financing. Since its start in 1990, the company has grown into one of Canada’s leading alternative lenders. As of September 30, 2025, GoEasy managed a consumer loan portfolio of $5.44 billion and reported $440 million in revenue for the quarter. Its mission is to support individuals with challenged credit by giving them access to financial products that can help rebuild their credit and improve their overall financial well‑being.

Sheet Assumptions & Methodology
A1: Model Purpose | B1: Equity valuation using Residual Income Model for goeasy Ltd.
A3: Key Assumptions
A4: ROE projections based on historical performance and normalization
A5: Cost of equity derived from CAPM-style estimate
A6: Terminal growth conservative and below nominal GDP
A8: Notes
A9: All blue cells across model indicate user inputs.

Sheet Contents
A1: No. | B1: Name | C1: Content
A2: 1 | B2: Financials | C2: Provides the historical financial data needed to understand GoEasy’s performance over the past five years, including net income, equity, ROE, and book value per share.
A3: 2 | B3: Market Data | C3: Shows how the market has valued GoEasy over time by tracking average share prices and valuation multiples such as P/E and P/B.
A4: 3 | B4: Valuation | C4: Uses historical earnings and book value to estimate GoEasy’s implied share price based on assumed valuation multiples.
A5: 4 | B5: Inputs | C5: Lists the key assumptions used in the valuation model, such as the risk‑free rate, beta, cost of equity, growth rate, and target ROE.
A6: 5 | B6: Residual Income Valuation | C6: Calculates the company’s future excess returns (Residual Income) and discounts them to determine GoEasy’s intrinsic value.
A7: 6 | B7: Valuation Summary | C7: Summarizes the final valuation results, including the present value of residual income, terminal value, and intrinsic value per share.
A8: 7 | B8: Sensitivity Analysis | C8: The sensitivity analysis tests how goeasy's value shifts when key inputs like ROE, credit defaults (net charge-offs), and the cost of equity are changed. By stressing these assumptions, it identifies the primary drivers of the stock's value and highlights the specific risks that could impact your investment thesis.
A9: 8 | B9: Financial Summary (1) | C9: Breaks down GoEasy’s income statement, balance sheet, and key financial metrics for multiple years to show trends in profitability and growth.
A10: 9 | B10: Shares outstanding | C10: Shows the number of diluted shares used in valuation calculations such as EPS and intrinsic value per share.
A11: 10 | B11: Financial Metrics | C11: Provides deeper performance ratios like ROA, ROE, return on receivables, margins, and adjusted profitability measures.
A12: 11 | B12: Income statement 2023 | C12: Gives a detailed breakdown of GoEasy’s 2023 revenue, expenses, and segment performance.
A13: 12 | B13: Income statement 2024 | C13: Provides the full 2024 income statement, including segment results and year‑over‑year changes.
... A18: 17 | B18: Error Checks | C18: Checking for errors

Sheet Financials
A1: Year | B1: Net Income | C1: Diluted EPS | D1: Equity | E1: Shares Outstanding | F1: BVPS | G1: ROE (%) | I1: Book Value Per Share (BVPS) = equity/ shares o/s
A2: 2020 | B2: 136505 | C2: 8.76 | D2: 443512 | E2: 15757 | F2: =Financial_no.[[#This Row],[Equity ]]/Financial_no.[[#This Row],[Shares Outstanding ]] -> 28.146982 | G2: 0.361 | I2: Return on equity (ROE) =Net Income /Equity
A3: 2021 | B3: 244943 | C3: 14.62 | D3: 789913 | E3: 16757 | F3: =Financial_no.[[#This Row],[Equity ]]/Financial_no.[[#This Row],[Shares Outstanding ]] -> 47.139285 | G3: 0.367
A4: 2022 | B4: 140161 | C4: 8.42 | D4: 869688 | E4: 16650 | F4: =Financial_no.[[#This Row],[Equity ]]/Financial_no.[[#This Row],[Shares Outstanding ]] -> 52.233514 | G4: 0.176
A5: 2023 | B5: 247898 | C5: 14.48 | D5: 1054077 | E5: 17117 | F5: =Financial_no.[[#This Row],[Equity ]]/Financial_no.[[#This Row],[Shares Outstanding ]] -> 61.580709 | G5: 0.259
A6: 2024 | B6: 283110 | C6: 16.3 | D6: 1201063 | E6: 17366 | F6: =Financial_no.[[#This Row],[Equity ]]/Financial_no.[[#This Row],[Shares Outstanding ]] -> 69.161753 | G6: 0.249
G8: *expressed in thousands

Sheet Market Data
A1: Year | B1: Avg Share Price | C1: P/E | D1: P/B | G1: P/E= Share price/EPS
A2: 2020 | B2: 63 | C2: =B2/Financials!C2 -> 7.1917808 | D2: =B2/Financials!F2 -> 2.2382506 | G2: P/B=Share price/BVPS
A3: 2021 | B3: 155 | C3: =B3/Financials!C3 -> 10.601915 | D3: =B3/Financials!F3 -> 3.2881279
A4: 2022 | B4: 110 | C4: =B4/Financials!C4 -> 13.064133 | D4: =B4/Financials!F4 -> 2.1059276
A5: 2023 | B5: 185 | C5: =B5/Financials!C5 -> 12.776243 | D5: =B5/Financials!F5 -> 3.0041875
A6: 2024 | B6: 175 | C6: =B6/Financials!C6 -> 10.736196 | D6: =B6/Financials!F6 -> 2.5303002

Sheet Valuation
A1: Assumed P/E Multiple | B1: 12
A2: Assumed P/B Multiple | B2: 3
A4: Year | B4: EPS | C4: Implied Price (P/E) | D4: BVPS | E4: Implied Price (P/B)
A5: =Financials!A2 -> 2020 | B5: =Financials!C2 -> 8.76 | C5: =Financials!C2*Valuation!B1 -> 105.12 | D5: =Financials!F2 -> 28.146982 | E5: =Financials!F2*Valuation!B2 -> 84.440947
A6: =Financials!A3 -> 2021 | B6: =Financials!C3 -> 14.62 | C6: =Financials!C3*Valuation!B1 -> 175.44 | D6: =Financials!F3 -> 47.139285 | E6: =Financials!F3*Valuation!B2 -> 141.41786
A7: =Financials!A4 -> 2022 | B7: =Financials!C4 -> 8.42 | C7: =Financials!C4*Valuation!B1 -> 101.04 | D7: =Financials!F4 -> 52.233514 | E7: =Financials!F4*Valuation!B2 -> 156.70054
A8: =Financials!A5 -> 2023 | B8: =Financials!C5 -> 14.48 | C8: =Financials!C5*Valuation!B1 -> 173.76 | D8: =Financials!F5 -> 61.580709 | E8: =Financials!F5*Valuation!B2 -> 184.74213
A9: =Financials!A6 -> 2024 | B9: =Financials!C6 -> 16.3 | C9: =Financials!C6*Valuation!B1 -> 195.6 | D9: =Financials!F6 -> 69.161753 | E9: =Financials!F6*Valuation!B2 -> 207.48526

Sheet Inputs
A1: Input | B1: Value | C1: Source / Rationale
A2: Risk-Free Rate | B2: 0.035 | C2: Approx. 10-Year Government Bond Yield. This is the yeild you would get from safe investments.
A3: Equity Risk Premium | B3: 0.055 | C3: Standard market premium. The extra returns an investor would want on their risky stocks.
A4: Beta | B4: 1.2 | C4: Estimated for a high-growth consumer lender. It is a measure of volatility.
A5: Cost of Equity (Ke​) | B5: 0.101 | C5: 3.5%+(1.2×5.5%). We can infer that Goeasy must earn greater than or equal to 10.10% to get good value.
A6: Target ROE | B6: 0.235 | C6: Mid-point of 2025-2027 guidance (23%+). As per the GoEasy annual report.
A7: Growth Rate (g) | B7: 0.04 | C7: Long-term terminal growth rate

Sheet Residual Income Valuation
A1: Metric (in $000s) | B1: 2024 (A) | C1: 2025 (E) | D1: 2026 (E) | E1: 2027 (E) | F1: Source / Rationale
A2: Beginning Equity | B2: - | C2: 1201063 | D2: 1483313 | E2: 1831892 | G2: Terminal Residual Income = {RI_{2027} * (1 + g)} / {Ke - g}
A3: Net Income (23.5% ROE) | B3: 283110 | C3: 282250 | D3: 348579 | E3: 430495 | F3: I took the Equity and multiplied it by the 23.5% ROE target.
A4: Equity Charge (10.1%) | B4: - | C4: -121307 | D4: -149815 | E4: -185021 | F4: I calculated what the "required" return was (Equity * 10.1% Cost of Equity). | G4: = {245,474 * 1.04} / {0.101 - 0.04} = $4,185,123
A5: Residual Income | B5: - | C5: 160943 | D5: 198764 | E5: 245474 | F5: Residual Income = Net Income - Equity. It represents the profit the company makes after satisfying its investors' minimum requirements.
A6: Discount Factor | B6: 1 | C6: 0.908 | D6: 0.825 | E6: 0.749 | G6: PV of Terminal Value: $4,185,123 * 0.749 = $3,134,657
A7: PV of Residual Income | B7: - | C7: 146136 | D7: 163980 | E7: 183860

Sheet Valuation Summary
A1: Component | B1: Amount (in $000s)
A2: Sum of PV of Residual Income (2025-2027) | B2: 493976
A3: PV of Terminal Value | B3: 3134657
A4: Total Value of Equity Premiums | B4: =B2+B3 -> 3628633
A5: (+) Current Book Value (End of 2024) | B5: 1201063
A6: Total Intrinsic Value | B6: =B2+B3+B5 -> 4829696
A7: Shares Outstanding | B7: 17366
A8: Intrinsic Value Per Share | B8: =B6/B7 -> 278.11217
A12: # Conclusion: Based on the company's guidance of maintaining an ROE above 23% and significantly growing the loan book to over $7 Billion by 2027, the stock is currently trading at a significant discount to its intrinsic value, provided they hit those growth targets without a spike in net charge-offs. The reason the model shows a high value ($278) compared to the current price ($175–$180) is simple: ROE vs. Cost of Equity. If a company can consistently earn 23.5% on its money while investors only "require" 10.1%, that company is a massive wealth-creation engine. The market price currently suggests that investors are skeptical that goeasy can maintain such a high ROE forever or are worried about potential loan losses if the economy weakens.
A14: To get the final "Intrinsic Value," I added three things:
A16: 1. The current Book Value ($1.2B)
A18: 2. + The present value of the next 3 years of Excess Returns.
A20: 3. + The present value of the Terminal Value.
A22: This gave us a total company value of roughly $4.83 Billion. When divided by the 17.37 Million shares, the result was $278.11 per share.

Sheet Sensitivity Analysis
A1: 1. ROE Sensitivity (Impact on Intrinsic Value per Share)
A3: Assumes Cost of Equity = 10.1%, g = 4%
A5: ROE | B5: Intrinsic Value/Share
A6: 0.21 | B6: ~$225
A7: 23% (Base Case) | B7: ~$278
A8: 0.25 | B8: ~$315
A9: 0.27 | B9: ~$350
A12: *GoEasy’s valuation is highly sensitive to ROE. A 2% drop in ROE reduces intrinsic value by ~20%, reflecting the importance of credit quality and loan growth.
A14: 2. Net Charge-Off (NCO) Sensitivity
A16: Assumes Loan Book ≈ $5.5B in 2025, every 0.5% change in NCO affects net income.
A18: NCO Rate | B18: Impact on Net Income | C18: Revised ROE | D18: Revised Value/Share
A19: 7.75% (Bull) | B19: +$20M | C19: ~25% | D19: ~$305
A20: 8.75% (Base) | B20: — | C20: ~23.5% | D20: ~$278
A21: 9.75% (Bear) | B21: –$30M | C21: ~21% | D21: ~$240
A23: *A 1% increase in charge-offs can reduce valuation by $35–40 per share, showing how credit losses are the biggest risk factor.
A25: 3. Cost of Equity (Ke) Sensitivity
A27: Assumes ROE = 23.5%, g = 4%
A29: Cost of Equity (Ke) | B29: Intrinsic Value/Share
A30: 0.09 | B30: ~$330
A31: 10.1% (Base) | B31: ~$278
A32: 0.11 | B32: ~$245
A33: 0.12 | B33: ~$215
A35: *Higher interest rates or higher perceived risk materially reduce valuation. A 1% increase in Ke lowers intrinsic value by ~12%.
A37: 4. Terminal Growth Rate (g) Sensitivity
A39: Assumes ROE = 23.5%, Ke = 10.1%
A41: Growth Rate (g) | B41: Intrinsic Value/Share
A42: 0.03 | B42: ~$250
A43: 4.0% (Base) | B43: ~$278
A44: 0.05 | B44: ~$310
A46: *GoEasy’s long-term value is moderately sensitive to growth assumptions, but less so than ROE or NCOs.
A49: #The valuation is most sensitive to ROE and credit losses, reflecting the nature of GoEasy’s lending business. Even small changes in NCOs or ROE materially impact intrinsic value, while growth assumptions have a more moderate effect. This highlights the importance of credit quality and disciplined underwriting in sustaining long-term shareholder value

Sheet Financial Summary (1)
A1: (in $000s except per share amounts, store counts, employee counts, percentages and ratios) | B1: 2024 | C1: 2023 | D1: 2022 | E1: 2021 | F1: 2020
A2: INCOME STATEMENT
A3: Revenue | B3: 1523289 | C3: 1250069 | D3: 1019336 | E3: 826722 | F3: 652,922
A4: Operating income | B4: 609657 | C4: 476518 | D4: 332407 | E4: 281003 | F4: 216,436
A5: Net income | B5: 283110 | C5: 247898 | D5: 140161 | E5: 244943 | F5: 136,505
A6: Diluted earnings per share | B6: 16.3 | C6: 14.48 | D6: 8.42 | E6: 14.62 | F6: 8.76
A7: BALANCE SHEET
A8: Cash | B8: 251381 | C8: 144577 | D8: 62654 | E8: 102479 | F8: 93,053
A9: Gross consumer loans receivable | B9: 4596115 | C9: 3645202 | D9: 2794694 | E9: 2030339 | F9: 1,246,840
A10: Lease assets | B10: 40973 | C10: 45187 | D10: 48437 | E10: 47182 | F10: 49,384
A11: Total assets | B11: 5194536 | C11: 4164167 | D11: 3302889 | E11: 2596153 | F11: 1,501,916
A12: External debt3 | B12: 3629803 | C12: 2819665 | D12: 2229260 | E12: 1552679 | F12: 887,749
A13: Shareholders’ equity | B13: 1201063 | C13: 1054077 | D13: 869688 | E13: 789913 | F13: 443,512
A14: FINANCIAL METRICS
A15: Revenue growth | B15: 0.219 | C15: 0.226 | D15: 0.233 | E15: 0.266 | F15: 7.10%
A16: Operating margin | B16: 0.4 | C16: 0.381 | D16: 0.326 | E16: 0.34 | F16: 33.10%
A17: Adjusted operating margin1 | B17: 0.412 | C17: 0.393 | D17: 0.362 | E17: 0.383 | F17: 33.10%
A18: Efficiency ratio1,4 | B18: 0.253 | C18: 0.302 | D18: 0.336 | E18: 0.372 | F18: -
A19: Adjusted net income2 | B19: 290142 | C19: 243175 | D19: 192261 | E19: 174759 | F19: 117,646

Sheet Shares outstanding

Sheet Balance Sheet 
A1: ($ IN 000’S, EXCEPT FOR RATIOS) | B1: DECEMBER 31, 2024 | C1: DECEMBER 31, 2023
A2: Consumer loans receivable, net | B2: 4366533 | C2: 3447588
A3: Cash | B3: 251381 | C3: 144577
A4: Accounts receivable | B4: 42438 | C4: 30762
A5: Prepaid expenses | B5: 9488 | C5: 9462
A6: Investments | B6: 41918 | C6: 61464
A7: Lease assets | B7: 40973 | C7: 45187
A8: Derivative financial assets | B8: 60675 | C8: 21904
A9: Property and equipment, net | B9: 35004 | C9: 35382
A10: Right-of-use assets, net | B10: 54224 | C10: 61987
A11: Intangible assets, net | B11: 110979 | C11: 124931
A12: Goodwill | B12: 180923 | C12: 180923
A13: Total assets | B13: 5194536 | C13: 4164167
... A29: Total capitalization (external debt plus total shareholders’ equity) | B29: 4830866 | C29: 3873742
A30: Capital management measures
A31: External debt to shareholders’ equity^{1} | B31: 3.02 | C31: 2.68
A32: Net debt to net capitalization^{2} | B32: 0.74 | C32: 0.72

Sheet Financial Metrics
A1: ($ IN 000’S EXCEPT PERCENTAGES AND PER SHARE AMOUNTS) | B1: 2024^{3} | C1: 2023^{3} | D1: 2022^{3} | E1: 2021^{3} | F1: 2020
A2: Gross Consumer Loans Receivable | B2: 4596115 | C2: 3645202 | D2: 2794694 | E2: 2,030,339 | F2: 1,246,840
A3: Revenue | B3: 1523289 | C3: 1250069 | D3: 1019336 | E3: 826,722 | F3: 652,922
A4: Net income | B4: 283110 | C4: 247898 | D4: 140161 | E4: 244,943 | F4: 136,505
A5: Adjusted net income^{1} | B5: 290142 | C5: 243175 | D5: 192261 | E5: 174,759 | F5: 117,646
A6: Return on receivables^{2} | B6: 0.068 | C6: 0.076 | D6: 0.058 | E6: - | F6: -
A7: Adjusted return on receivables^{1,2} | B7: 0.07 | C7: 0.075 | D7: 0.08 | E7: - | F7: -
A8: Return on assets | B8: 0.061 | C8: 0.067 | D8: 0.048 | E8: 11.5% | F8: 9.8%
A9: Adjusted return on assets^{1} | B9: 0.062 | C9: 0.065 | D9: 0.066 | E9: 8.2% | F9: 8.5%
A10: Return on equity | B10: 0.249 | C10: 0.259 | D10: 0.176 | E10: 36.7% | F10: 36.1%
A11: Adjusted return on equity^{1} | B11: 0.255 | C11: 0.254 | D11: 0.242 | E11: 26.2% | F11: 31.1%
A12: Return on tangible common equity^{1} | B12: 0.328 | C12: 0.367 | D12: 0.284 | E12: 50.7% | F12: 38.3%
A13: Adjusted return on tangible common equity^{1} | B13: 0.325 | C13: 0.346 | D13: 0.364 | E13: 35.3% | F13: 33.0%
... A20: Adjusted diluted^{1} | B20: 16.71 | C20: 14.21 | D20: 11.55 | E20: 10.43 | F20: 7.57

Sheet Income statement 2023
A1: ($ IN 000'S EXCEPT EARNINGS PER SHARE) | B1: EASYFINANCIAL | C1: EASYHOME (Dec 31, 2023) | D1: CORPORATE | E1: TOTAL
A2: Revenue
A3: Interest income | B3: 853,228 | C3: 35700 | D3: - | E3: 888928
A4: Lease revenue | B4: - | C4: 99848 | D4: - | E4: 99848
A5: Commissions earned | B5: 220,363 | C5: 14122 | D5: - | E5: 234485
A6: Charges and fees | B6: 23,226 | C6: 3582 | D6: - | E6: 26808
A7: Total | B7: 1,096,817 | C7: 153252 | D7: - | E7: 1250069
A8: Operating expenses
A9: Bad debts | B9: 327,196 | C9: 14443 | D9: - | E9: 341639
A10: Other operating expenses | B10: 197,358 | C10: 59610 | D10: 88,613 | E10: 345581
A11: Depreciation and amortization | B11: 37,747 | C11: 42259 | D11: 6,325 | E11: 86331
A12: Total | B12: 562,301 | C12: 116312 | D12: 94,938 | E12: 773551
A13: Operating income (loss) | B13: 534,516 | C13: 36940 | D13: (94,938) | E13: 476518
A14: Other income | E14: 9771
A15: Finance costs | E15: -149334
A16: Income before income taxes | E16: 336955
A17: Income taxes | E17: 89057
A18: Net income | E18: 247898
A19: Diluted earnings per share | E19: 14.48

Sheet Income Statement 2024
A1: ($ IN 000'S EXCEPT EARNINGS PER SHARE) | B1: EASYFINANCIAL | C1: EASYHOME (Dec 31, 2024) | D1: CORPORATE | E1: TOTAL
A2: Revenue
A3: Interest income | B3: 1,081,843 | C3: 39979 | D3: - | E3: 1121822
A4: Lease revenue | B4: - | C4: 95407 | D4: - | E4: 95407
A5: Commissions earned | B5: 261,630 | C5: 14096 | D5: - | E5: 275726
A6: Charges and fees | B6: 26,941 | C6: 3393 | D6: - | E6: 30334
A7: Total | B7: 1,370,414 | C7: 152875 | D7: - | E7: 1523289
A8: Operating expenses
A9: Bad debts | B9: 452,558 | C9: 15206 | D9: - | E9: 467764
A10: Other operating expenses | B10: 212,451 | C10: 54987 | D10: 94,535 | E10: 361973
A11: Depreciation and amortization | B11: 38,995 | C11: 38096 | D11: 6,804 | E11: 83895
A12: Total | B12: 704,004 | C12: 108289 | D12: 101,339 | E12: 913632
A13: Operating income (loss) | B13: 666,410 | C13: 44586 | D13: (101,339) | E13: 609657
A14: Other income | E14: 3132
A15: Finance costs | E15: -225492
A16: Income before income taxes | E16: 387297
A17: Income taxes | E17: 104187
A18: Net income | E18: 283110
A19: Diluted earnings per share | E19: 16.3

Sheet Financial Summary (2)
A1: Column1 | B1: YEAR | C1: ENDED | D1: Column4 | E1: Column5
A2: - | B2: DECEMBER 31, | C2: DECEMBER 31, | D2: VARIANCE | E2: VARIANCE
A3: ($ IN 000’S EXCEPT EARNINGS PER SHARE AND PERCENTAGES) | B3: 2024 | C3: 2023 | D3: $ / BPS | E3: % CHANGE
A4: Summary Financial Results | B4: - | C4: - | D4: - | E4: -
A5: Revenue | B5: 1,523,289 | C5: 1,250,069 | D5: 273,220 | E5: 21.9%
A6: Bad debts | B6: 467,764 | C6: 341,639 | D6: 126,125 | E6: 36.9%
A7: Other operating expenses | B7: 361,973 | C7: 345,581 | D7: 16,392 | E7: 4.7%
A8: EBITDA^{1} | B8: 667,202 | C8: 539,085 | D8: 128,117 | E8: 23.8%
A9: EBITDA margin^{1} | B9: 43.8% | C9: 43.1% | D9: 70 bps | E9: 1.6%
A10: Depreciation and amortization | B10: 83,895 | C10: 86,331 | D10: (2,436) | E10: (2.8%)
A11: Operating income | B11: 609,657 | C11: 476,518 | D11: 133,139 | E11: 27.9%
A12: Operating margin | B12: 40.0% | C12: 38.1% | D12: 190 bps | E12: 5.0%
... A46: Potential monthly leasing revenue^{1} | B46: 6,875 | C46: 7,654 | D46: (779) | E46: (10.2%)

Sheet Previous ROE
A1: Column1 | B1: ACTUAL RESULTS FOR 2024 | C1: UPDATED FORECASTS FOR 2024 | D1: OUTCOME
A2: Gross consumer loans receivable at year-end | B2: $4.60 billion | C2: $4.55 - $4.65 billion | D2: Consistent with forecast
A3: Total Company revenue | B3: $1.52 billion | C3: $1.50 - $1.60 billion | D3: Consistent with forecast
A4: Total yield on consumer loans (including ancillary products)^{1} | B4: 34.1 % | C4: 33.0% - 35.0% | D4: Consistent with forecast
A5: Net charge offs as a percentage of average gross consumer loans receivable | B5: 9.2% | C5: 8.0% - 10.0% | D5: Consistent with forecast
A6: Total Company operating margin (reported/adjusted^{1,2} ) | B6: 40.0%/41.2% | C6: 39% + | D6: Consistent with forecast
A7: Return on equity (reported/adjusted^{1,2} ) | B7: 24.9%/25.5% | C7: 21% + | D7: Consistent with forecast

Sheet Projected ROE
A1: Column1 | B1: FORECASTS FOR 2025 | C1: FORECASTS FOR 2026 | D1: FORECASTS FOR 2027
A2: Gross consumer loans receivable at year end | B2: $5.40 - $5.70 Billion | C2: $6.40 - $6.70 Billion | D2: $7.35 - $7.75 Billion
A3: Total Company revenue | B3: $1.62 - $1.82 Billion | C3: $1.80 - $2.00 Billion | D3: $2.00 - $2.20 Billion
A4: Total yield on consumer loans (including ancillary products)^{1} | B4: 31.0% - 32.5% | C4: 29.0% - 31.0% | D4: 29.0% - 31.0%
A5: Net charge offs as a percentage of average gross consumer loans receivable | B5: 7.75% - 9.75% | C5: 7.5% - 9.5% | D5: 7.5% - 9.5%
A6: Total Company operating margin | B6: 41% + | C6: 42.5% + | D6: 43% +
A7: Return on equity | B7: 23% + | C7: 23% + | D7: 23% +
B21: N

Sheet Bad Debts
A1: ($ IN 000’S) | B1: DECEMBER 31, 2024 | C1: DECEMBER 31, 2023
A2: Provision required due to net charge offs | B2: 383494 | C2: 289321
A3: Impact of loan book growth | B3: 60808 | C3: 57466
A4: Impact of change in allowance for expected credit losses rate | B4: 23462 | C4: -5148
A5: Net change in allowance for credit losses | B5: 84270 | C5: 52318
A6: Bad debt expense | B6: 467764 | C6: 341639

Sheet Error Checks
A1: Check | B1: Formula | C1: Status
A2: Balance Sheet Balances | B2: Assets = Liabilities + Equity (manual review) | C2: OK
